{
    "about": "The Nichols plot is a plot used in signal processing and control design, named after American engineer N.B Nichols.[1][2][3]", 
    "name": "Nichols Plot", 
    "classification": "Signal Processing", 
    "full_text": "The Nichols plot is a plot used in signal processing and control design, named after American engineer N.B Nichols.[1][2][3]\n\n\nGiven a transfer function,\n\n\n\n\nG\n(\ns\n)\n=\n\n\n\nY\n(\ns\n)\n\n\nX\n(\ns\n)\n\n\n\n\n\n{\\displaystyle G(s)={\\frac {Y(s)}{X(s)}}}\n\n\nwith the closed-loop transfer function defined as,\n\n\n\n\nM\n(\ns\n)\n=\n\n\n\nG\n(\ns\n)\n\n\n1\n+\nG\n(\ns\n)\n\n\n\n\n\n{\\displaystyle M(s)={\\frac {G(s)}{1+G(s)}}}\n\n\nthe Nichols plots displays \n\n\n\n20\n\nlog\n\n10\n\n\n\u2061\n(\n\n|\n\nG\n(\ns\n)\n\n|\n\n)\n\n\n{\\displaystyle 20\\log _{10}(|G(s)|)}\n\n versus \n\n\n\narg\n\u2061\n(\nG\n(\ns\n)\n)\n\n\n{\\displaystyle \\arg(G(s))}\n\n. Loci of constant \n\n\n\n20\n\nlog\n\n10\n\n\n\u2061\n(\n\n|\n\nM\n(\ns\n)\n\n|\n\n)\n\n\n{\\displaystyle 20\\log _{10}(|M(s)|)}\n\n and \n\n\n\narg\n\u2061\n(\nM\n(\ns\n)\n)\n\n\n{\\displaystyle \\arg(M(s))}\n\n are overlaid to allow the designer to obtain the closed loop transfer function directly from the open loop transfer function. Thus, the frequency \n\n\n\n\u03c9\n\n\n{\\displaystyle \\omega }\n\n is the parameter along the curve. This plot may be compared to the Bode plot in which the two inter-related graphs - \n\n\n\n20\n\nlog\n\n10\n\n\n\u2061\n(\n\n|\n\nG\n(\ns\n)\n\n|\n\n)\n\n\n{\\displaystyle 20\\log _{10}(|G(s)|)}\n\n versus \n\n\n\n\nlog\n\n10\n\n\n\u2061\n(\n\u03c9\n)\n\n\n{\\displaystyle \\log _{10}(\\omega )}\n\n and \n\n\n\narg\n\u2061\n(\nG\n(\ns\n)\n)\n\n\n{\\displaystyle \\arg(G(s))}\n\n versus \n\n\n\n\nlog\n\n10\n\n\n\u2061\n(\n\u03c9\n)\n\n\n{\\displaystyle \\log _{10}(\\omega )}\n\n) - are plotted.\nIn feedback control design, the plot is useful for assessing the stability and robustness of a linear system. This application of the Nichols plot is central to the Quantitative feedback theory (QFT) of Horowitz and Sidi, which is a well known method for robust control system design.\nIn most cases, \n\n\n\narg\n\u2061\n(\nG\n(\ns\n)\n)\n\n\n{\\displaystyle \\arg(G(s))}\n\n refers to the phase of the system's response. Although similar to a Nyquist plot, a Nichols plot is plotted in a Cartesian coordinate system while a Nyquist plot is plotted in a polar coordinate system.", 
    "dbpedia_url": "http://dbpedia.org/resource/Nichols_plot", 
    "wikipedia_url": "http://en.wikipedia.org/wiki/Nichols_plot\n"
}